{
    "os": "Linux-6.8.0-47-generic-x86_64-with-glibc2.39",
    "python": "3.12.0",
    "heartbeatAt": "2024-10-27T17:33:34.446720",
    "startedAt": "2024-10-27T17:33:33.728152",
    "docker": null,
    "cuda": null,
    "args": [
        "--output_dir",
        "/home/drdo/Caricatures/models/scan_distilgpt2_ppo",
        "--model_checkpoint",
        "/home/drdo/Caricatures/models/scan_distilgpt2/checkpoint-40000"
    ],
    "state": "running",
    "program": "/home/drdo/Caricatures/experiments/rl_expts/gpt2_scan_ppo.py",
    "codePathLocal": "gpt2_scan_ppo.py",
    "codePath": "experiments/rl_expts/gpt2_scan_ppo.py",
    "git": {
        "remote": "https://github.com/tatami-galaxy/Caricatures.git",
        "commit": "94bd5bbcbd386190381b4130692a7783c5d482c3"
    },
    "email": "ujandev@gmail.com",
    "root": "/home/drdo/Caricatures",
    "host": "drdo-omen-4090",
    "username": "drdo",
    "executable": "/home/drdo/anaconda3/envs/nlp/bin/python",
    "cpu_count": 24,
    "cpu_count_logical": 32,
    "cpu_freq": {
        "current": 1636.56884375,
        "min": 800.0,
        "max": 5050.0
    },
    "cpu_freq_per_core": [
        {
            "current": 1251.932,
            "min": 800.0,
            "max": 5800.0
        },
        {
            "current": 800.0,
            "min": 800.0,
            "max": 5800.0
        },
        {
            "current": 800.0,
            "min": 800.0,
            "max": 5800.0
        },
        {
            "current": 800.0,
            "min": 800.0,
            "max": 5800.0
        },
        {
            "current": 800.335,
            "min": 800.0,
            "max": 5800.0
        },
        {
            "current": 800.0,
            "min": 800.0,
            "max": 5800.0
        },
        {
            "current": 1000.35,
            "min": 800.0,
            "max": 5800.0
        },
        {
            "current": 800.0,
            "min": 800.0,
            "max": 5800.0
        },
        {
            "current": 5680.083,
            "min": 800.0,
            "max": 5800.0
        },
        {
            "current": 800.0,
            "min": 800.0,
            "max": 5800.0
        },
        {
            "current": 2156.896,
            "min": 800.0,
            "max": 5800.0
        },
        {
            "current": 800.0,
            "min": 800.0,
            "max": 5800.0
        },
        {
            "current": 800.0,
            "min": 800.0,
            "max": 5800.0
        },
        {
            "current": 800.0,
            "min": 800.0,
            "max": 5800.0
        },
        {
            "current": 800.0,
            "min": 800.0,
            "max": 5800.0
        },
        {
            "current": 800.0,
            "min": 800.0,
            "max": 5800.0
        },
        {
            "current": 800.0,
            "min": 800.0,
            "max": 4300.0
        },
        {
            "current": 801.58,
            "min": 800.0,
            "max": 4300.0
        },
        {
            "current": 800.0,
            "min": 800.0,
            "max": 4300.0
        },
        {
            "current": 800.0,
            "min": 800.0,
            "max": 4300.0
        },
        {
            "current": 800.0,
            "min": 800.0,
            "max": 4300.0
        },
        {
            "current": 800.0,
            "min": 800.0,
            "max": 4300.0
        },
        {
            "current": 800.0,
            "min": 800.0,
            "max": 4300.0
        },
        {
            "current": 3555.175,
            "min": 800.0,
            "max": 4300.0
        },
        {
            "current": 800.0,
            "min": 800.0,
            "max": 4300.0
        },
        {
            "current": 798.878,
            "min": 800.0,
            "max": 4300.0
        },
        {
            "current": 800.0,
            "min": 800.0,
            "max": 4300.0
        },
        {
            "current": 800.0,
            "min": 800.0,
            "max": 4300.0
        },
        {
            "current": 800.0,
            "min": 800.0,
            "max": 4300.0
        },
        {
            "current": 800.0,
            "min": 800.0,
            "max": 4300.0
        },
        {
            "current": 2595.642,
            "min": 800.0,
            "max": 4300.0
        },
        {
            "current": 4301.223,
            "min": 800.0,
            "max": 4300.0
        }
    ],
    "disk": {
        "/": {
            "total": 937.3305015563965,
            "used": 405.63064193725586
        }
    },
    "gpu": "NVIDIA GeForce RTX 4090",
    "gpu_count": 1,
    "gpu_devices": [
        {
            "name": "NVIDIA GeForce RTX 4090",
            "memory_total": 25757220864
        }
    ],
    "memory": {
        "total": 62.4819450378418
    }
}
